Metadata-Version: 2.1
Name: test_package_open_face
Version: 0.0.1
Summary: A sample test package
Home-page: https://github.com/mohankashyap/test-tackage
Author: pargim
Author-email: mohan.tita@gmail.com
License: MIT
Platform: UNKNOWN
Requires-Python: >=3.6
License-File: LICENSE
